{
  "questions": [
    {
      "text": "Texto pergunta",
      "points": {
        "fullyDisagree": 1,
        "partiallyDisagree": 1,
        "dontKnow": 2,
        "partiallyAgree": 2,
        "fullyAgree": 3
      },
      "id": "2365"
    },
    {
      "id": "471c",
      "text": "Escreva sua pergunta...",
      "points": {
        "fullyDesagree": null,
        "partiallyDisagree": null,
        "dontKnow": null,
        "partiallyAgree": null,
        "fullyAgree": null
      }
    }
  ],
  "results": [
    {
      "id": "1",
      "name": "Backend",
      "description": "Você seria um programador Backend"
    },
    {
      "id": "2",
      "name": "Frontend",
      "description": "Você seria um programador Frontend"
    },
    {
      "id": "3",
      "name": "Mobile",
      "description": "Você seria um programador Mobile"
    }
  ]
}